MANIFEST.in
Makefile.in
README.rst
devconfig.sh
devnotes.rst
setup.py
bibtools/__init__.py
bibtools/ads.py
bibtools/apj-issnmap.txt
bibtools/arxiv.py
bibtools/bibcore.py
bibtools/bibtex.py
bibtools/cli.py
bibtools/completions.py
bibtools/config.py
bibtools/crossref.py
bibtools/db.py
bibtools/defaults.cfg
bibtools/fetchpdf.py
bibtools/proxy.py
bibtools/schema.sql
bibtools/secret.py
bibtools/textfmt.py
bibtools/unicode_to_latex.py
bibtools/util.py
bibtools/webutil.py
bibtools.egg-info/PKG-INFO
bibtools.egg-info/SOURCES.txt
bibtools.egg-info/dependency_links.txt
bibtools.egg-info/entry_points.txt
bibtools.egg-info/not-zip-safe
bibtools.egg-info/pbr.json
bibtools.egg-info/requires.txt
bibtools.egg-info/top_level.txt
bibtools/hacked_bibtexparser/__init__.py
bibtools/hacked_bibtexparser/bparser.py
bibtools/hacked_bibtexparser/customization.py
bibtools/hacked_bibtexparser/info.py
bibtools/hacked_bibtexparser/latexenc.py