Metadata-Version: 1.0
Name: bibtools
Version: 0.3
Summary: Command-line bibliography manager
Home-page: https://github.com/pkgw/bibtools/
Author: Peter Williams
Author-email: peter@newton.cx
License: GPLv3
Keywords: bibliography
Platform: UNKNOWN
